justllms/__init__.py
justllms/__version__.py
justllms/cli.py
justllms/config/__init__.py
justllms/config/config.py
justllms/core/__init__.py
justllms/core/base.py
justllms/core/client.py
justllms/core/completion.py
justllms/core/models.py
justllms/core/openai_base.py
justllms/core/streaming.py
justllms/data/__init__.py
justllms/exceptions/__init__.py
justllms/exceptions/exceptions.py
justllms/providers/__init__.py
justllms/providers/anthropic.py
justllms/providers/azure_openai.py
justllms/providers/deepseek.py
justllms/providers/google.py
justllms/providers/grok.py
justllms/providers/ollama.py
justllms/providers/openai.py
justllms/routing/__init__.py
justllms/routing/router.py
justllms/sxs/__init__.py
justllms/sxs/cli.py
justllms/sxs/core/__init__.py
justllms/sxs/core/executor.py
justllms/sxs/models/__init__.py
justllms/sxs/models/comparison.py
justllms/tools/__init__.py
justllms/tools/decorators.py
justllms/tools/executor.py
justllms/tools/google.py
justllms/tools/models.py
justllms/tools/registry.py
justllms/tools/utils.py
justllms/tools/adapters/__init__.py
justllms/tools/adapters/anthropic.py
justllms/tools/adapters/azure.py
justllms/tools/adapters/base.py
justllms/tools/adapters/google.py
justllms/tools/adapters/openai.py
justllms/tools/native/__init__.py
justllms/tools/native/google_tools.py
justllms/tools/native/manager.py
justllms/utils/__init__.py
justllms/utils/token_counter.py
justllms/utils/validators.py
justllms-2.1.8.dist-info/licenses/LICENSE
justllms-2.1.8.dist-info/METADATA
justllms-2.1.8.dist-info/WHEEL
justllms-2.1.8.dist-info/entry_points.txt
justllms-2.1.8.dist-info/top_level.txt
justllms-2.1.8.dist-info/RECORD
