Metadata-Version: 2.4
Name: justllms
Version: 2.1.8
Summary: Production-focused Python library for multi-provider LLM management with unified API
Author-email: darshan harihar <darshanharihar2950@gmail.com>
License: MIT
Project-URL: Homepage, https://github.com/just-llms/justllms
Project-URL: Documentation, https://github.com/just-llms/justllms#readme
Project-URL: Repository, https://github.com/just-llms/justllms
Project-URL: Bug Tracker, https://github.com/just-llms/justllms/issues
Keywords: llm,ai,openai,anthropic,gemini,gateway,proxy
Classifier: Development Status :: 4 - Beta
Classifier: Intended Audience :: Developers
Classifier: License :: OSI Approved :: MIT License
Classifier: Programming Language :: Python :: 3
Classifier: Programming Language :: Python :: 3.8
Classifier: Programming Language :: Python :: 3.9
Classifier: Programming Language :: Python :: 3.10
Classifier: Programming Language :: Python :: 3.11
Classifier: Programming Language :: Python :: 3.12
Classifier: Topic :: Software Development :: Libraries :: Python Modules
Classifier: Topic :: Scientific/Engineering :: Artificial Intelligence
Requires-Python: >=3.8
License-File: LICENSE
Requires-Dist: httpx>=0.25.0
Requires-Dist: pydantic>=2.0.0
Requires-Dist: tenacity>=8.0.0
Requires-Dist: tiktoken>=0.5.0
Requires-Dist: python-dotenv>=1.0.0
Requires-Dist: rich>=13.0.0
Requires-Dist: PyYAML>=6.0.0
Requires-Dist: click>=8.0.0
Requires-Dist: questionary>=2.0.0
Provides-Extra: dev
Requires-Dist: pytest>=7.0.0; extra == "dev"
Requires-Dist: pytest-asyncio>=0.21.0; extra == "dev"
Requires-Dist: pytest-cov>=4.0.0; extra == "dev"
Requires-Dist: black>=23.0.0; extra == "dev"
Requires-Dist: ruff>=0.1.0; extra == "dev"
Requires-Dist: mypy>=1.0.0; extra == "dev"
Requires-Dist: pre-commit>=3.0.0; extra == "dev"
Provides-Extra: docs
Requires-Dist: sphinx>=6.0.0; extra == "docs"
Requires-Dist: sphinx-rtd-theme>=1.3.0; extra == "docs"
Requires-Dist: sphinx-autodoc-typehints>=1.24.0; extra == "docs"
Requires-Dist: myst-parser>=2.0.0; extra == "docs"
Provides-Extra: providers
Requires-Dist: openai>=1.0.0; extra == "providers"
Requires-Dist: anthropic>=0.18.0; extra == "providers"
Requires-Dist: google-generativeai>=0.3.0; extra == "providers"
Requires-Dist: cohere>=4.0.0; extra == "providers"
Requires-Dist: replicate>=0.15.0; extra == "providers"
Provides-Extra: analytics
Requires-Dist: reportlab>=4.0.0; extra == "analytics"
Requires-Dist: matplotlib>=3.5.0; extra == "analytics"
Requires-Dist: pandas>=1.3.0; extra == "analytics"
Dynamic: license-file
